oc_orm_initializator/__init__.py
oc_orm_initializator/orm_initializator.py
oc_orm_initializator-1.1.0.dist-info/LICENSE
oc_orm_initializator-1.1.0.dist-info/METADATA
oc_orm_initializator-1.1.0.dist-info/WHEEL
oc_orm_initializator-1.1.0.dist-info/top_level.txt
oc_orm_initializator-1.1.0.dist-info/RECORD
